fastsecrets-0.2.0.dist-info/METADATA
fastsecrets-0.2.0.dist-info/WHEEL
fastsecrets-0.2.0.dist-info/entry_points.txt
fastsecrets-0.2.0.dist-info/licenses/LICENSE.md
fastsecrets.libs/libgcc_s-f5fcfe20.so.1
fastsecrets/__init__.py
fastsecrets/__main__.py
fastsecrets/cli.py
fastsecrets/fastsecrets.cpython-310-i386-linux-gnu.so
fastsecrets-0.2.0.dist-info/RECORD
